apolis_ai_tools/__init__.py
apolis_ai_tools/compat.py
apolis_ai_tools/cores/__init__.py
apolis_ai_tools/cores/doc_parser_core/__init__.py
apolis_ai_tools/cores/doc_parser_core/app.py
apolis_ai_tools/cores/doc_parser_core/domain.py
apolis_ai_tools/cores/doc_parser_core/extraction_policy.py
apolis_ai_tools/cores/doc_parser_core/layout.py
apolis_ai_tools/cores/doc_parser_core/layout_service.py
apolis_ai_tools/cores/doc_parser_core/ocr_service.py
apolis_ai_tools/cores/doc_parser_core/pdf_reader.py
apolis_ai_tools/cores/doc_parser_core/server.py
apolis_ai_tools/cores/email_core/__init__.py
apolis_ai_tools/cores/email_core/client.py
apolis_ai_tools/cores/email_core/utils.py
apolis_ai_tools/cores/outlook_core/__init__.py
apolis_ai_tools/cores/outlook_core/client.py
apolis_ai_tools/cores/validation_core/__init__.py
apolis_ai_tools/cores/validation_core/domain.py
apolis_ai_tools/cores/validation_core/presets.py
apolis_ai_tools/cores/validation_core/validator.py
apolis_ai_tools/mlcore/__init__.py
apolis_ai_tools/mlcore/registry.py
apolis_ai_tools/mlcore/inference/__init__.py
apolis_ai_tools/mlcore/models/README.md
apolis_ai_tools/mlcore/models/__init__.py
apolis_ai_tools/mlcore/training/__init__.py
apolis_ai_tools/tools/__init__.py
apolis_ai_tools/tools/doc_parser/__init__.py
apolis_ai_tools/tools/doc_parser/tool.py
apolis_ai_tools/tools/gmail_tools/__init__.py
apolis_ai_tools/tools/gmail_tools/draft/__init__.py
apolis_ai_tools/tools/gmail_tools/draft/tool.py
apolis_ai_tools/tools/gmail_tools/search/__init__.py
apolis_ai_tools/tools/gmail_tools/search/tool.py
apolis_ai_tools/tools/gmail_tools/send/__init__.py
apolis_ai_tools/tools/gmail_tools/send/tool.py
apolis_ai_tools/tools/outlook_tools/__init__.py
apolis_ai_tools/tools/outlook_tools/search/__init__.py
apolis_ai_tools/tools/outlook_tools/search/tool.py
apolis_ai_tools/tools/outlook_tools/send/__init__.py
apolis_ai_tools/tools/outlook_tools/send/tool.py
apolis_ai_tools/tools/validation/__init__.py
apolis_ai-0.3.0.dist-info/METADATA
apolis_ai-0.3.0.dist-info/WHEEL
apolis_ai-0.3.0.dist-info/top_level.txt
apolis_ai-0.3.0.dist-info/RECORD
