Metadata-Version: 2.4
Name: apolis_ai
Version: 0.3.0
Summary: Internal CrewAI tools and cores - Distributed via Private PyPI
Project-URL: repository, https://github.com/apolisapps/apolis_ai
Requires-Python: >=3.10
Requires-Dist: crewai
Requires-Dist: pydantic<3.0.0,>=2.7.0
Requires-Dist: pydantic-settings>=2.11.0
Requires-Dist: requests>=2.31.0
Requires-Dist: python-dotenv
Provides-Extra: gmail
Provides-Extra: outlook
Provides-Extra: ocr
Requires-Dist: paddleocr>=2.7.0; extra == "ocr"
Requires-Dist: paddlepaddle>=2.6.0; extra == "ocr"
Requires-Dist: opencv-python>=4.9.0; extra == "ocr"
Requires-Dist: Pillow>=10.2.0; extra == "ocr"
Requires-Dist: pdfplumber==0.10.4; extra == "ocr"
Requires-Dist: docling>=2.0.0; extra == "ocr"
Requires-Dist: deepsearch-toolkit; extra == "ocr"
Requires-Dist: fastapi>=0.109.0; extra == "ocr"
Requires-Dist: uvicorn>=0.27.0; extra == "ocr"
Requires-Dist: numpy; extra == "ocr"
Provides-Extra: dev
Requires-Dist: pytest==8.1.1; extra == "dev"
